[
    {
        "id": "1071",
        "first_name": "Kyle",
        "last_name": "Thomas",
        "company": "Startup Company",
        "company_domain": "https:\/\/startupcompany.com",
        "email": "kyle.thomas@startupcompany.com",
        "phone": "15554115757",
        "associated_accounts": [
            44,
            45,
            42,
            46
        ]
    },
    {
        "id": "1122",
        "first_name": "Joseph",
        "last_name": "Jordan",
        "company": "Startup Company",
        "company_domain": "https:\/\/startupcompany.com",
        "email": "joseph.jordan@startupcompany.com",
        "phone": null,
        "associated_accounts": []
    },
    {
        "id": "1183",
        "first_name": "Joyce",
        "last_name": "Willie",
        "company": "Big Company",
        "company_domain": "https:\/\/bigcompany.com",
        "email": "joyce.willie@bigcompany.com",
        "phone": "15555648522",
        "associated_accounts": [
            45,
            46,
            43
        ]
    },
    {
        "id": "1249",
        "first_name": "Doris",
        "last_name": "Jerry",
        "company": "Startup Company",
        "company_domain": "https:\/\/startupcompany.com",
        "email": "djerry@startupcompany.com",
        "phone": "15559690566",
        "associated_accounts": [
            43
        ]
    },
    {
        "id": "1307",
        "first_name": "Jonathan",
        "last_name": "Terry",
        "company": "Corporate Company",
        "company_domain": "https:\/\/corporatecompany.com",
        "email": "jonathan.terry@corporatecompany.com",
        "phone": "15553255828",
        "associated_accounts": []
    },
    {
        "id": "1358",
        "first_name": "Peter",
        "last_name": "Denise",
        "company": "Unicorn Company",
        "company_domain": "https:\/\/unicorncompany.com",
        "email": "peter.denise@unicorncompany.com",
        "phone": "15553390265",
        "associated_accounts": [
            44,
            41,
            42,
            45
        ]
    },
    {
        "id": "1426",
        "first_name": "Sophia",
        "last_name": "Jeffrey",
        "company": "Startup Company",
        "company_domain": "https:\/\/startupcompany.com",
        "email": "sjeffrey@startupcompany.com",
        "phone": "15558358130",
        "associated_accounts": [
            40
        ]
    },
    {
        "id": "1490",
        "first_name": "Jerry",
        "last_name": "Madison",
        "company": "Corporate Company",
        "company_domain": "https:\/\/corporatecompany.com",
        "email": "jerry.madison@corporatecompany.com",
        "phone": "15551491564",
        "associated_accounts": [
            43,
            44,
            45
        ]
    },
    {
        "id": "1544",
        "first_name": "Joshua",
        "last_name": "Justin",
        "company": "Corporate Company",
        "company_domain": "https:\/\/corporatecompany.com",
        "email": "joshua.justin@corporatecompany.com",
        "phone": null,
        "associated_accounts": [
            42
        ]
    },
    {
        "id": "1606",
        "first_name": "Andrew",
        "last_name": "Judith",
        "company": "Small Company",
        "company_domain": "https:\/\/smallcompany.com",
        "email": "ajudith@smallcompany.com",
        "phone": "15554259904",
        "associated_accounts": [
            41,
            45,
            42
        ]
    },
    {
        "id": "1675",
        "first_name": "Gabriel",
        "last_name": "Edward",
        "company": "Corporate Company",
        "company_domain": "https:\/\/corporatecompany.com",
        "email": "gabriel.edward@corporatecompany.com",
        "phone": "15558085682",
        "associated_accounts": [
            46
        ]
    },
    {
        "id": "1741",
        "first_name": "Joe",
        "last_name": "Joyce",
        "company": "Corporate Company",
        "company_domain": "https:\/\/corporatecompany.com",
        "email": "joe.joyce@corporatecompany.com",
        "phone": "15558460618",
        "associated_accounts": [
            40,
            45
        ]
    },
    {
        "id": "1792",
        "first_name": "Barbara",
        "last_name": "Ronald",
        "company": "Corporate Company",
        "company_domain": "https:\/\/corporatecompany.com",
        "email": "barbara.ronald@corporatecompany.com",
        "phone": null,
        "associated_accounts": [
            45
        ]
    },
    {
        "id": "1860",
        "first_name": "Charlotte",
        "last_name": "Randy",
        "company": "Unicorn Company",
        "company_domain": "https:\/\/unicorncompany.com",
        "email": "charlotte.randy@unicorncompany.com",
        "phone": null,
        "associated_accounts": [
            41,
            46,
            42
        ]
    },
    {
        "id": "1919",
        "first_name": "Logan",
        "last_name": "Diane",
        "company": "Unicorn Company",
        "company_domain": "https:\/\/unicorncompany.com",
        "email": "logan.diane@unicorncompany.com",
        "phone": "15556035295",
        "associated_accounts": [
            41,
            46
        ]
    },
    {
        "id": "1977",
        "first_name": "Ashley",
        "last_name": "Patricia",
        "company": "Startup Company",
        "company_domain": "https:\/\/startupcompany.com",
        "email": "ashley.patricia@startupcompany.com",
        "phone": null,
        "associated_accounts": [
            42,
            44,
            45,
            39
        ]
    },
    {
        "id": "2030",
        "first_name": "Adam",
        "last_name": "Debra",
        "company": "Startup Company",
        "company_domain": "https:\/\/startupcompany.com",
        "email": "adebra@startupcompany.com",
        "phone": "15551734601",
        "associated_accounts": [
            39,
            44,
            45
        ]
    },
    {
        "id": "2089",
        "first_name": "Tyler",
        "last_name": "Carl",
        "company": "Small Company",
        "company_domain": "https:\/\/smallcompany.com",
        "email": "tyler.carl@smallcompany.com",
        "phone": "15552542324",
        "associated_accounts": [
            44
        ]
    },
    {
        "id": "2153",
        "first_name": "Michelle",
        "last_name": "Brian",
        "company": "Startup Company",
        "company_domain": "https:\/\/startupcompany.com",
        "email": "michelle.brian@startupcompany.com",
        "phone": "15553925557",
        "associated_accounts": [
            42,
            46
        ]
    },
    {
        "id": "2213",
        "first_name": "Louis",
        "last_name": "Brian",
        "company": "Small Company",
        "company_domain": "https:\/\/smallcompany.com",
        "email": "louis.brian@smallcompany.com",
        "phone": "15557438293",
        "associated_accounts": [
            45,
            42,
            61
        ]
    },
    {
        "id": "2265",
        "first_name": "Louis",
        "last_name": "Pamela",
        "company": "Startup Company",
        "company_domain": "https:\/\/startupcompany.com",
        "email": "lpamela@startupcompany.com",
        "phone": "15551038624",
        "associated_accounts": [
            45,
            46,
            41
        ]
    },
    {
        "id": "2321",
        "first_name": "Kimberly",
        "last_name": "Jeremy",
        "company": "Big Company",
        "company_domain": "https:\/\/bigcompany.com",
        "email": "kimberly.jeremy@bigcompany.com",
        "phone": "15551365768",
        "associated_accounts": []
    },
    {
        "id": "2385",
        "first_name": "Debra",
        "last_name": "Jacqueline",
        "company": "Small Company",
        "company_domain": "https:\/\/smallcompany.com",
        "email": "djacqueline@smallcompany.com",
        "phone": null,
        "associated_accounts": [
            42,
            46
        ]
    },
    {
        "id": "2443",
        "first_name": "Gary",
        "last_name": "Lawrence",
        "company": "Big Company",
        "company_domain": "https:\/\/bigcompany.com",
        "email": "gary.lawrence@bigcompany.com",
        "phone": "15550433689",
        "associated_accounts": []
    },
    {
        "id": "2495",
        "first_name": "Jason",
        "last_name": "Charles",
        "company": "Corporate Company",
        "company_domain": "https:\/\/corporatecompany.com",
        "email": "jason.charles@corporatecompany.com",
        "phone": null,
        "associated_accounts": [
            45,
            40,
            41
        ]
    },
    {
        "id": "2564",
        "first_name": "Teresa",
        "last_name": "Theresa",
        "company": "Corporate Company",
        "company_domain": "https:\/\/corporatecompany.com",
        "email": "ttheresa@corporatecompany.com",
        "phone": "15557717012",
        "associated_accounts": [
            41,
            42
        ]
    },
    {
        "id": "2626",
        "first_name": "Nicole",
        "last_name": "Noah",
        "company": "Corporate Company",
        "company_domain": "https:\/\/corporatecompany.com",
        "email": "nicole.noah@corporatecompany.com",
        "phone": null,
        "associated_accounts": [
            39
        ]
    },
    {
        "id": "2689",
        "first_name": "Angela",
        "last_name": "Gary",
        "company": "Unicorn Company",
        "company_domain": "https:\/\/unicorncompany.com",
        "email": "angela.gary@unicorncompany.com",
        "phone": "15559339503",
        "associated_accounts": [
            42,
            41,
            45
        ]
    },
    {
        "id": "2752",
        "first_name": "Brian",
        "last_name": "Keith",
        "company": "Big Company",
        "company_domain": "https:\/\/bigcompany.com",
        "email": "brian.keith@bigcompany.com",
        "phone": "15558221465",
        "associated_accounts": [
            42,
            41,
            39
        ]
    }
]